odoo/addons/account_move_batch_validate/README.rst
odoo/addons/account_move_batch_validate/__init__.py
odoo/addons/account_move_batch_validate/__manifest__.py
odoo/addons/account_move_batch_validate/i18n/account_move_batch_validate.pot
odoo/addons/account_move_batch_validate/i18n/am.po
odoo/addons/account_move_batch_validate/i18n/ar.po
odoo/addons/account_move_batch_validate/i18n/bg.po
odoo/addons/account_move_batch_validate/i18n/bs.po
odoo/addons/account_move_batch_validate/i18n/ca.po
odoo/addons/account_move_batch_validate/i18n/ca_ES.po
odoo/addons/account_move_batch_validate/i18n/cs.po
odoo/addons/account_move_batch_validate/i18n/de.po
odoo/addons/account_move_batch_validate/i18n/en_GB.po
odoo/addons/account_move_batch_validate/i18n/es.po
odoo/addons/account_move_batch_validate/i18n/es_CR.po
odoo/addons/account_move_batch_validate/i18n/es_EC.po
odoo/addons/account_move_batch_validate/i18n/es_ES.po
odoo/addons/account_move_batch_validate/i18n/es_MX.po
odoo/addons/account_move_batch_validate/i18n/es_VE.po
odoo/addons/account_move_batch_validate/i18n/et.po
odoo/addons/account_move_batch_validate/i18n/fr.po
odoo/addons/account_move_batch_validate/i18n/gl.po
odoo/addons/account_move_batch_validate/i18n/gl_ES.po
odoo/addons/account_move_batch_validate/i18n/gu.po
odoo/addons/account_move_batch_validate/i18n/hr.po
odoo/addons/account_move_batch_validate/i18n/hr_HR.po
odoo/addons/account_move_batch_validate/i18n/hu.po
odoo/addons/account_move_batch_validate/i18n/id.po
odoo/addons/account_move_batch_validate/i18n/it.po
odoo/addons/account_move_batch_validate/i18n/ja.po
odoo/addons/account_move_batch_validate/i18n/lt.po
odoo/addons/account_move_batch_validate/i18n/mk.po
odoo/addons/account_move_batch_validate/i18n/mn.po
odoo/addons/account_move_batch_validate/i18n/nb.po
odoo/addons/account_move_batch_validate/i18n/nl.po
odoo/addons/account_move_batch_validate/i18n/nl_BE.po
odoo/addons/account_move_batch_validate/i18n/pl.po
odoo/addons/account_move_batch_validate/i18n/pt.po
odoo12_addon_account_move_batch_validate-12.0.1.0.0.99.dev6.dist-info/METADATA
odoo12_addon_account_move_batch_validate-12.0.1.0.0.99.dev6.dist-info/WHEEL
odoo12_addon_account_move_batch_validate-12.0.1.0.0.99.dev6.dist-info/top_level.txt
odoo12_addon_account_move_batch_validate-12.0.1.0.0.99.dev6.dist-info/RECORD
